presto_drf/__init__.py
presto_drf/mixins.py
presto_drf/parsers.py
presto_drf/renderers.py
presto_drf-0.0.2.dist-info/LICENSE
presto_drf-0.0.2.dist-info/METADATA
presto_drf-0.0.2.dist-info/WHEEL
presto_drf-0.0.2.dist-info/top_level.txt
presto_drf-0.0.2.dist-info/RECORD
