Metadata-Version: 2.1
Name: presto-drf
Version: 0.0.2
Summary: Integration package for using django-rest-framework with prestojs
Home-page: https://github.com/prestojs/prestojs/
Author: Alliance Software
Author-email: support@alliancesoftware.com.au
License: UNKNOWN
Keywords: rad,rapid application development,drf,rest,django
Platform: UNKNOWN
Classifier: Programming Language :: Python :: 3
Classifier: License :: OSI Approved :: MIT License
Classifier: Operating System :: OS Independent
Requires-Python: >=3.6
Requires-Dist: djangorestframework (>=3.8)
